{
  "ticker": "BDLL4",
  "nome": "BARDELLA S.A. INDUSTRIAS MECANICAS",
  "inicio_negociacao": "26/11/1969",
  "cnpj": "60.851.615/0001-53",
  "sobre": "Bens de capital. Produtos e Serviços para os segmentos de Metalurgia. Movimentação de Materiais. Óleo e Gás. Energia e Aços Laminados e Trefilados. para os mercados nacionais e internacional",
  "setor_economico": "Bens Industriais",
  "subsetor": "Máquinas e Equipamentos",
  "segmento": "Máq. e Equip. Industriais",
  "site": "www.bardella.com.br",
  "dados_economico_financeiros": {
    "balanco_patrimonial": {
      "datas": [
        "31/03/2025",
        "31/12/2024",
        "01/01/2025",
        "31/03/2025",
        "01/01/2024",
        "31/03/2024",
        "01/01/2025",
        "31/03/2025",
        "01/01/2024",
        "31/03/2024"
      ],
      "valores": {}
    }
  },
  "posicao_acionaria": [],
  "acoes_em_circulacao_no_mercado": [],
  "composicao_capital_social": null
}