{
  "ticker": "CAML3",
  "nome": "CAMIL ALIMENTOS S.A.",
  "inicio_negociacao": "28/09/2017",
  "cnpj": "64.904.295/0001-03",
  "sobre": "Industrialização e comercialização de grãos. pescados. açúcar. massas. biscoitos e café.",
  "setor_economico": "Consumo não Cíclico",
  "subsetor": "Alimentos Processados",
  "segmento": "Alimentos Diversos",
  "site": "www.camilalimentos.com.br",
  "dados_economico_financeiros": "Ver dados no formato Consolidado  Não consolidado Balanço Patrimonial  - Consolidado28/02/202528/02/2024Ativo Imobilizado, Investimentos e Intangível4.042.8313.615.377Ativo Total11.106.59510.621.358Patrimônio Líquido3.457.5903.087.346Patrimônio Líquido Atribuído à Controladora3.457.3223.087.100Demonstração do Resultado - Consolidado01/03/2024 a 28/02/202501/03/2023 a 28/02/2024Receita de Venda12.262.93911.249.647Resultado Bruto2.389.9482.275.972Resultado de Equivalência Patrimonial(4.166)1.083Resultado Financeiro(464.367)(423.730)Resultado Líquido das Operações Continuadas217.001360.461Lucro (Prejuízo) do Período217.001360.461Lucro (Prejuízo) do Período Atribuído à Controladora216.950360.337Demonstração do Fluxo de Caixa - Consolidado01/03/2024 a 28/02/202501/03/2023 a 28/02/2024Atividades Operacionais831.364554.854Atividades de Investimento(586.988)(311.992)Atividades de Financiamento(564.718)1.303.879Variação Cambial sobre Caixa e Equivalentes50.29027.901Aumento (Redução) de Caixa e Equivalentes(270.052)1.574.642",
  "posicao_acionaria": "Nome%ON%PN%TotalCamil Investimentos S.A.51,430,0051,43JACQUES MAGGI QUARTIERO5,690,005,69LUCIANO MAGGI QUARTIERO7,460,007,46THIAGO MAGGI QUARTIERO5,380,005,38OUTROS27,490,0027,49AÇÕES TESOURARIA2,550,002,55TOTAL100,000,00100,00Informação recebida em 08/07/2025. (*) Posição dos acionistas com mais de 5% das ações de cada espécie.",
  "acoes_em_circulacao_no_mercado": "08/07/2025Tipos de Investidores / AçõesQuantidadePercentualPessoas Físicas36.898-Pessoas Jurídicas129-Investidores Institucionais199-Quantidade de Ações Ordinárias95.981.12427,42Total de Ações95.981.12427,42",
  "composicao_capital_social": "01/02/2023Ordinárias350.000.000Preferenciais0Total350.000.000"
}