{
  "ticker": "EUCA3",
  "nome": "EUCATEX S.A. INDUSTRIA E COMERCIO",
  "inicio_negociacao": "20/08/1969",
  "cnpj": "56.643.018/0001-66",
  "sobre": "Indústria e Comércio de chapas de fibra de madeira",
  "setor_economico": "Materiais Básicos",
  "subsetor": "Madeira e Papel",
  "segmento": "Madeira",
  "site": "www.eucatex.com.br/ri",
  "dados_economico_financeiros": {
    "balanco_patrimonial": {
      "ativo_imobilizado_investimentos_e_intangivel": {
        "31/03/2025": 2538623,
        "31/12/2024": 2497666
      },
      "ativo_total": {
        "31/03/2025": 4854633,
        "31/12/2024": 4569192
      },
      "patrimônio_liquido": {
        "31/03/2025": 2652814,
        "31/12/2024": 2570690
      },
      "patrimônio_liquido_atribuido_à_controladora": {
        "31/03/2025": 2652916,
        "31/12/2024": 2570790
      }
    },
    "demonstracao_resultado": {
      "receita_de_venda": {
        "01/01/2025_a_31/03/2025": 744713,
        "01/01/2024_a_31/03/2024": 641002
      },
      "resultado_bruto": {
        "01/01/2025_a_31/03/2025": 279233,
        "01/01/2024_a_31/03/2024": 213310
      },
      "resultado_de_equivalencia_patrimonial": {
        "01/01/2025_a_31/03/2025": 0,
        "01/01/2024_a_31/03/2024": 0
      },
      "resultado_financeiro": {
        "01/01/2025_a_31/03/2025": 14219,
        "01/01/2024_a_31/03/2024": -18996
      },
      "resultado_liquido_das_operacões_continuadas": {
        "01/01/2025_a_31/03/2025": 95962,
        "01/01/2024_a_31/03/2024": 53304
      },
      "lucro_prejuizo_do_periodo": {
        "01/01/2025_a_31/03/2025": 95960,
        "01/01/2024_a_31/03/2024": 53301
      },
      "lucro_prejuizo_do_periodo_atribuido_à_controladora": {
        "01/01/2025_a_31/03/2025": 0,
        "01/01/2024_a_31/03/2024": 0
      }
    },
    "fluxo_caixa": {
      "atividades_operacionais": {
        "01/01/2025_a_31/03/2025": 75583,
        "01/01/2024_a_31/03/2024": 92129
      },
      "atividades_de_investimento": {
        "01/01/2025_a_31/03/2025": -74058,
        "01/01/2024_a_31/03/2024": -99089
      },
      "atividades_de_financiamento": {
        "01/01/2025_a_31/03/2025": 220980,
        "01/01/2024_a_31/03/2024": -130
      },
      "variacao_cambial_sobre_caixa_e_equivalentes": {
        "01/01/2025_a_31/03/2025": 0,
        "01/01/2024_a_31/03/2024": 0
      },
      "aumento_reducao_de_caixa_e_equivalentes": {
        "01/01/2025_a_31/03/2025": 222505,
        "01/01/2024_a_31/03/2024": -7090
      }
    }
  },
  "posicao_acionaria": [
    {
      "nome": "APOLLO PARTICIPAÇÕES S.A.",
      "ON": 34.34,
      "PN": 0.0,
      "Total": 11.58
    },
    {
      "nome": "Brascorp Participações Ltda",
      "ON": 11.77,
      "PN": 0.0,
      "Total": 3.97
    },
    {
      "nome": "Economico Agro Pastoril Industrial S/A",
      "ON": 0.0,
      "PN": 50.28,
      "Total": 33.32
    },
    {
      "nome": "FABIO TORRES MALUF",
      "ON": 0.0,
      "PN": 0.03,
      "Total": 0.02
    },
    {
      "nome": "FLAVIO MALUF",
      "ON": 6.5,
      "PN": 0.14,
      "Total": 2.29
    },
    {
      "nome": "Grandfood Ind. e Comercio Ltda",
      "ON": 0.0,
      "PN": 6.59,
      "Total": 4.37
    },
    {
      "nome": "Grandfood Ind. e Comércio Ltda",
      "ON": 0.0,
      "PN": 0.8,
      "Total": 0.53
    },
    {
      "nome": "IFF Holding S.A.",
      "ON": 39.97,
      "PN": 8.09,
      "Total": 18.84
    },
    {
      "nome": "OTAVIO MALUF",
      "ON": 4.55,
      "PN": 0.07,
      "Total": 1.58
    },
    {
      "nome": "PAULO SALIM MALUF",
      "ON": 0.97,
      "PN": 0.13,
      "Total": 0.41
    },
    {
      "nome": "UBS Ag Zurich",
      "ON": 0.0,
      "PN": 9.81,
      "Total": 6.5
    },
    {
      "nome": "OUTROS",
      "ON": 1.88,
      "PN": 23.29,
      "Total": 16.07
    },
    {
      "nome": "AÇÕES TESOURARIA",
      "ON": 0.02,
      "PN": 0.77,
      "Total": 0.52
    },
    {
      "nome": "TOTAL",
      "ON": 100.0,
      "PN": 100.0,
      "Total": 100.0
    }
  ],
  "acoes_em_circulacao_no_mercado": {
    "tipos_investidores": [
      {
        "tipo": "Pessoas Físicas",
        "quantidade": 7000,
        "percentual": null
      },
      {
        "tipo": "Pessoas Jurídicas",
        "quantidade": 113,
        "percentual": null
      },
      {
        "tipo": "Investidores Institucionais",
        "quantidade": 64,
        "percentual": null
      },
      {
        "tipo": "Quantidade de Ações Preferenciais",
        "quantidade": 51146941,
        "percentual": 83.24
      }
    ],
    "data": "24/04/2025",
    "quantidade_acoes_ordinarias": 588537,
    "percentual_ordinarias": 1.88,
    "total_acoes": 51735478,
    "percentual_total": 55.81
  },
  "composicao_capital_social": {
    "data": "25/04/2024",
    "preferenciais": 61361556,
    "total": 92619256
  }
}