{
  "ticker": "ODPV3",
  "nome": "ODONTOPREV S.A.",
  "inicio_negociacao": "01/12/2006",
  "cnpj": "58.119.199/0001-51",
  "sobre": "Operadora de planos odontológicos",
  "setor_economico": "Saúde",
  "subsetor": "Serv.Méd.Hospit..Análises e Diagnósticos",
  "segmento": "Serv.Méd.Hospit..Análises e Diagnósticos (segmento)",
  "site": "www.odontoprev.com.br/ri",
  "dados_economico_financeiros": "Ver dados no formato Consolidado  Não consolidado Balanço Patrimonial  - Consolidado31/03/202531/12/2024Ativo Imobilizado, Investimentos e Intangível978.760978.302Ativo Total2.235.9032.122.069Patrimônio Líquido1.364.7731.228.233Patrimônio Líquido Atribuído à Controladora1.364.4641.227.769Demonstração do Resultado - Consolidado01/01/2025 a 31/03/202501/01/2024 a 31/03/2024Receita de Venda587.800554.501Resultado Bruto255.700209.031Resultado de Equivalência Patrimonial1.7781.056Resultado Financeiro15.17023.625Resultado Líquido das Operações Continuadas169.569146.689Lucro (Prejuízo) do Período169.569146.689Lucro (Prejuízo) do Período Atribuído à Controladora169.724146.737Demonstração do Fluxo de Caixa - Consolidado01/01/2025 a 31/03/202501/01/2024 a 31/03/2024Atividades Operacionais53.46953.406Atividades de Investimento(16.740)(33.839)Atividades de Financiamento(31.643)(21.106)Variação Cambial sobre Caixa e Equivalentes00Aumento (Redução) de Caixa e Equivalentes5.086(1.539)",
  "posicao_acionaria": "Nome%ON%PN%TotalBradesco Saúde S/A53,540,0053,54OUTROS46,420,0046,42AÇÕES TESOURARIA0,050,000,05TOTAL100,000,00100,00Informação recebida em 29/05/2025. (*) Posição dos acionistas com mais de 5% das ações de cada espécie.",
  "acoes_em_circulacao_no_mercado": "01/04/2025Tipos de Investidores / AçõesQuantidadePercentualPessoas Físicas50.629-Pessoas Jurídicas230-Investidores Institucionais251-Quantidade de Ações Ordinárias252.219.52146,21Total de Ações252.219.52146,21",
  "composicao_capital_social": "01/04/2025Ordinárias545.825.286Preferenciais0Total545.825.286"
}